odoo/addons/mrp_bom_structure_xlsx/README.rst
odoo/addons/mrp_bom_structure_xlsx/__init__.py
odoo/addons/mrp_bom_structure_xlsx/__manifest__.py
odoo/addons/mrp_bom_structure_xlsx/i18n/de.po
odoo/addons/mrp_bom_structure_xlsx/i18n/it.po
odoo/addons/mrp_bom_structure_xlsx/i18n/mrp_bom_structure_xlsx.pot
odoo/addons/mrp_bom_structure_xlsx/readme/CONTRIBUTORS.rst
odoo/addons/mrp_bom_structure_xlsx/readme/DESCRIPTION.rst
odoo/addons/mrp_bom_structure_xlsx/readme/INSTALL.rst
odoo/addons/mrp_bom_structure_xlsx/readme/USAGE.rst
odoo/addons/mrp_bom_structure_xlsx/report/__init__.py
odoo/addons/mrp_bom_structure_xlsx/report/bom_structure_xlsx.py
odoo/addons/mrp_bom_structure_xlsx/report/bom_structure_xlsx.xml
odoo/addons/mrp_bom_structure_xlsx/static/description/icon.png
odoo/addons/mrp_bom_structure_xlsx/static/description/index.html
odoo12_addon_mrp_bom_structure_xlsx-12.0.1.0.0.99.dev16.dist-info/METADATA
odoo12_addon_mrp_bom_structure_xlsx-12.0.1.0.0.99.dev16.dist-info/WHEEL
odoo12_addon_mrp_bom_structure_xlsx-12.0.1.0.0.99.dev16.dist-info/top_level.txt
odoo12_addon_mrp_bom_structure_xlsx-12.0.1.0.0.99.dev16.dist-info/RECORD
